Cb_FloodDy/__init__.py
Cb_FloodDy/bayesian_opt_tuning.py
Cb_FloodDy/cli.py
Cb_FloodDy/model_prediction.py
Cb_FloodDy/model_training.py
Cb_FloodDy/utils.py
Cb_FloodDy/voronoi_clusters.py
cb_flooddy-0.4.1.dist-info/METADATA
cb_flooddy-0.4.1.dist-info/WHEEL
cb_flooddy-0.4.1.dist-info/top_level.txt
cb_flooddy-0.4.1.dist-info/RECORD
