Metadata-Version: 2.1
Name: cb-flooddy
Version: 0.4.1
Summary: A cluster-based temporal attention approach for predicting cyclone-induced compound flood dynamics
Author: Samuel Daramola
License: MIT
Project-URL: Homepage, https://pypi.org/project/Cb-FloodDy/
Project-URL: Repository, https://github.com/SamuelDara/Cb_FloodDy.git
Classifier: Programming Language :: Python :: 3
Classifier: License :: OSI Approved :: MIT License
Classifier: Operating System :: OS Independent
Classifier: Intended Audience :: Science/Research
Classifier: Topic :: Scientific/Engineering :: GIS
Classifier: Topic :: Scientific/Engineering :: Artificial Intelligence
Requires-Python: >=3.9
Requires-Dist: numpy
Requires-Dist: pandas
Requires-Dist: matplotlib
Requires-Dist: scipy
Requires-Dist: geopandas
Requires-Dist: shapely
Requires-Dist: pyproj
Requires-Dist: rasterio
Requires-Dist: scikit-learn
Requires-Dist: tensorflow (>=2.9)
Requires-Dist: optuna (>=3.0)
